PartSeg/__init__.py
PartSeg/__main__.py
PartSeg/changelog.py
PartSeg/launcher_main.py
PartSeg/napari.yaml
PartSeg/state_store.py
PartSeg/version.py
PartSeg/_launcher/__init__.py
PartSeg/_launcher/check_survey.py
PartSeg/_launcher/check_version.py
PartSeg/_launcher/main_window.py
PartSeg/_roi_analysis/__init__.py
PartSeg/_roi_analysis/advanced_window.py
PartSeg/_roi_analysis/batch_window.py
PartSeg/_roi_analysis/calculation_pipeline_thread.py
PartSeg/_roi_analysis/export_batch.py
PartSeg/_roi_analysis/image_view.py
PartSeg/_roi_analysis/main_window.py
PartSeg/_roi_analysis/measurement_widget.py
PartSeg/_roi_analysis/partseg_settings.py
PartSeg/_roi_analysis/prepare_plan_widget.py
PartSeg/_roi_analysis/profile_export.py
PartSeg/_roi_mask/__init__.py
PartSeg/_roi_mask/batch_proceed.py
PartSeg/_roi_mask/image_view.py
PartSeg/_roi_mask/main_window.py
PartSeg/_roi_mask/segmentation_info_dialog.py
PartSeg/_roi_mask/simple_measurements.py
PartSeg/_roi_mask/stack_settings.py
PartSeg/common_backend/__init__.py
PartSeg/common_backend/abstract_class.py
PartSeg/common_backend/base_argparser.py
PartSeg/common_backend/base_settings.py
PartSeg/common_backend/except_hook.py
PartSeg/common_backend/load_backup.py
PartSeg/common_backend/partially_const_dict.py
PartSeg/common_backend/progress_thread.py
PartSeg/common_backend/python_syntax_highlight.py
PartSeg/common_backend/segmentation_thread.py
PartSeg/common_gui/__init__.py
PartSeg/common_gui/about_dialog.py
PartSeg/common_gui/advanced_tabs.py
PartSeg/common_gui/algorithms_description.py
PartSeg/common_gui/channel_control.py
PartSeg/common_gui/collapse_checkbox.py
PartSeg/common_gui/colormap_creator.py
PartSeg/common_gui/custom_buttons.py
PartSeg/common_gui/custom_load_dialog.py
PartSeg/common_gui/custom_save_dialog.py
PartSeg/common_gui/dict_viewer.py
PartSeg/common_gui/equal_column_layout.py
PartSeg/common_gui/error_report.py
PartSeg/common_gui/exception_hooks.py
PartSeg/common_gui/flow_layout.py
partseg-0.16.4.dist-info/licenses/License.txt
partseg-0.16.4.dist-info/METADATA
partseg-0.16.4.dist-info/WHEEL
partseg-0.16.4.dist-info/entry_points.txt
partseg-0.16.4.dist-info/top_level.txt
partseg-0.16.4.dist-info/RECORD
