Metadata-Version: 2.4
Name: PartSeg
Version: 0.16.4
Summary: PartSeg is python GUI and set of napari plugins for bio imaging analysis especially nucleus analysis,
Author-email: Grzegorz Bokota <g.bokota@uw.edu.pl>
License-Expression: BSD-3-Clause
Project-URL: Homepage, https://partseg.github.io/
Project-URL: Documentation, https://partseg.readthedocs.io/en/stable/
Project-URL: Source Code, https://github.com/4DNucleome/PartSeg
Project-URL: User Support, https://github.com/4DNucleome/PartSeg/issues
Project-URL: Bug Tracker, https://github.com/4DNucleome/PartSeg/issues
Keywords: bioimaging,GUI
Platform: Linux
Platform: Windows
Platform: MacOs
Classifier: Development Status :: 3 - Alpha
Classifier: Framework :: napari
Classifier: Operating System :: OS Independent
Classifier: Programming Language :: Python :: 3
Classifier: Programming Language :: Python :: 3 :: Only
Classifier: Programming Language :: Python :: 3.9
Classifier: Programming Language :: Python :: 3.10
Classifier: Programming Language :: Python :: 3.11
Classifier: Programming Language :: Python :: 3.12
Classifier: Programming Language :: Python :: Implementation :: CPython
Classifier: Topic :: Scientific/Engineering :: Bio-Informatics
Classifier: Topic :: Scientific/Engineering :: Image Processing
Classifier: Topic :: Scientific/Engineering :: Visualization
Requires-Python: >=3.9
License-File: License.txt
Requires-Dist: IPython>=7.7.0
Requires-Dist: PartSegCore-compiled-backend<0.16.0,>=0.13.11
Requires-Dist: PartSegData==0.10.0
Requires-Dist: QtAwesome!=1.2.0,>=1.0.3
Requires-Dist: QtPy>=1.10.0
Requires-Dist: SimpleITK>=2.1.0
Requires-Dist: appdirs>=1.4.4
Requires-Dist: czifile>=2019.5.22
Requires-Dist: defusedxml>=0.6.0
Requires-Dist: fonticon-fontawesome6>=6.1.1
Requires-Dist: h5py>=3.3.0
Requires-Dist: imagecodecs>=2020.5.30
Requires-Dist: imageio>=2.20.0
Requires-Dist: ipykernel>=5.2.0
Requires-Dist: local-migrator>=0.1.7
Requires-Dist: magicgui>=0.7.0
Requires-Dist: mahotas>=1.4.12
Requires-Dist: napari>=0.5.0
Requires-Dist: nme>=0.1.7
Requires-Dist: numpy>=1.22.2; python_version >= "3.10"
Requires-Dist: numpy<2,>=1.22.2; python_version < "3.10"
Requires-Dist: oiffile>=2020.1.18
Requires-Dist: openpyxl>=3.0.7
Requires-Dist: packaging>=22.0
Requires-Dist: pandas>=1.3.0
Requires-Dist: psygnal>=0.5.0
Requires-Dist: pydantic<3,>=1.9.1
Requires-Dist: pygments>=2.12.0
Requires-Dist: qtconsole>=4.7.7
Requires-Dist: requests>=2.25.0
Requires-Dist: scipy>=1.5.4
Requires-Dist: sentry-sdk>=2.4.0
Requires-Dist: six>=1.11.0
Requires-Dist: superqt>=0.6.7
Requires-Dist: sympy>=1.10
Requires-Dist: tifffile>=2022.4.8
Requires-Dist: traceback-with-variables>=2.0.4
Requires-Dist: vispy>=0.14.1
Requires-Dist: xlrd>=1.1.0
Requires-Dist: xlsxwriter>=2.0.0
Provides-Extra: accelerate
Provides-Extra: all
Requires-Dist: PartSeg[accelerate,pyqt5]; extra == "all"
Provides-Extra: docs
Requires-Dist: autodoc-pydantic; extra == "docs"
Requires-Dist: sphinx!=3.0.0,!=3.5.0; extra == "docs"
Requires-Dist: sphinx-autodoc-typehints; extra == "docs"
Requires-Dist: sphinx-qt-documentation; extra == "docs"
Provides-Extra: pyinstaller
Requires-Dist: PartSeg[pyinstaller_base,pyqt5]; extra == "pyinstaller"
Provides-Extra: pyinstaller-base
Requires-Dist: PartSeg[accelerate]; extra == "pyinstaller-base"
Requires-Dist: PyInstaller; extra == "pyinstaller-base"
Requires-Dist: pydantic; extra == "pyinstaller-base"
Provides-Extra: pyqt
Requires-Dist: PartSeg[pyqt5]; extra == "pyqt"
Provides-Extra: pyqt5
Requires-Dist: PyQt5!=5.15.0,>=5.12.3; extra == "pyqt5"
Requires-Dist: napari[pyqt5]; extra == "pyqt5"
Provides-Extra: pyqt6
Requires-Dist: PyQt6; extra == "pyqt6"
Requires-Dist: napari[pyqt6]>=0.5.0; extra == "pyqt6"
Provides-Extra: pyside
Requires-Dist: PartSeg[pyside2]; extra == "pyside"
Provides-Extra: pyside2
Requires-Dist: PySide2!=5.15.0,>=5.12.3; extra == "pyside2"
Requires-Dist: napari[pyside]; extra == "pyside2"
Provides-Extra: pyside6
Requires-Dist: PySide6; extra == "pyside6"
Requires-Dist: napari[pyside6_experimental]>=0.5.0; extra == "pyside6"
Provides-Extra: test
Requires-Dist: coverage; extra == "test"
Requires-Dist: lxml[html_clean]; extra == "test"
Requires-Dist: pytest>=7.0.0; extra == "test"
Requires-Dist: pytest-qt; extra == "test"
Requires-Dist: pytest-timeout; extra == "test"
Requires-Dist: scikit-image; extra == "test"
Provides-Extra: testing
Requires-Dist: pytest; extra == "testing"
Requires-Dist: pytest-qt; extra == "testing"
Requires-Dist: lxml; extra == "testing"
Dynamic: description
Dynamic: description-content-type
Dynamic: license-file
